smithspump/comm.cp36-win32.pyd
smithspump-0.1.3.dist-info/METADATA
smithspump-0.1.3.dist-info/WHEEL
smithspump-0.1.3.dist-info/top_level.txt
smithspump-0.1.3.dist-info/RECORD
