Metadata-Version: 2.1
Name: smithspump
Version: 0.1.3
Summary: A libary to connect smiths medical pump
Home-page: UNKNOWN
Author: Samuel Chen
Author-email: 
License: UNKNOWN
Keywords: library smiths pump
Platform: UNKNOWN
Classifier: Development Status :: 5 - Production/Stable
Classifier: Intended Audience :: Developers
Classifier: Topic :: Software Development :: Libraries :: Python Modules
Classifier: License :: OSI Approved :: MIT License
Classifier: Programming Language :: Python :: 3
Classifier: Programming Language :: Python :: 3.6
Requires-Python: ==3.6.*
Requires-Dist: optenum
Requires-Dist: pyserial
Provides-Extra: dev
Requires-Dist: check-manifest ; extra == 'dev'
Provides-Extra: test
Requires-Dist: coverage ; extra == 'test'
